marshmallow_configparser/__init__.py
marshmallow_configparser/compatibility.py
marshmallow_configparser/convenience_fields.py
marshmallow_configparser/fields.py
marshmallow_configparser/helpers.py
marshmallow_configparser/schema.py
marshmallow_configparser/validators.py
marshmallow_configparser-0.4.0.dist-info/METADATA
marshmallow_configparser-0.4.0.dist-info/RECORD
marshmallow_configparser-0.4.0.dist-info/WHEEL
marshmallow_configparser-0.4.0.dist-info/top_level.txt
