Metadata-Version: 2.1
Name: marshmallow-configparser
Version: 0.4.0
Summary: ConfigParser meets marshmallow
Home-page: https://github.com/tadams42/marshmallow_configparser
Author: Tomislav Adamic
Author-email: tomislav.adamic@gmail.com
License: MIT
Keywords: congfiparser,marshmallow
Platform: UNKNOWN
Classifier: Development Status :: 4 - Beta
Classifier: Intended Audience :: Developers
Classifier: License :: OSI Approved :: MIT License
Classifier: Programming Language :: Python
Classifier: Programming Language :: Python :: 2.7
Classifier: Programming Language :: Python :: 3
Classifier: Programming Language :: Python :: 3.5
Classifier: Programming Language :: Python :: 3.6
Classifier: Programming Language :: Python :: Implementation :: CPython
Classifier: Programming Language :: Python :: Implementation :: PyPy
Classifier: Operating System :: OS Independent
Classifier: Topic :: Software Development :: Libraries :: Python Modules
Provides-Extra: dev
Provides-Extra: docs
Requires-Dist: marshmallow
Provides-Extra: dev
Requires-Dist: bumpversion; extra == 'dev'
Requires-Dist: check-manifest; extra == 'dev'
Requires-Dist: coverage; extra == 'dev'
Requires-Dist: factory-boy; extra == 'dev'
Requires-Dist: faker; extra == 'dev'
Requires-Dist: ipython; extra == 'dev'
Requires-Dist: isort; extra == 'dev'
Requires-Dist: m2r; extra == 'dev'
Requires-Dist: pycodestyle; extra == 'dev'
Requires-Dist: pylint; extra == 'dev'
Requires-Dist: pytest-cov; extra == 'dev'
Requires-Dist: pytest-mock; extra == 'dev'
Requires-Dist: pytest-sugar; extra == 'dev'
Requires-Dist: pytest (>=3.0.0); extra == 'dev'
Requires-Dist: sphinx; extra == 'dev'
Requires-Dist: sphinx-rtd-theme; extra == 'dev'
Requires-Dist: yapf; extra == 'dev'
Provides-Extra: docs
Requires-Dist: m2r (>=0.1.14); extra == 'docs'
Requires-Dist: sphinx (>=1.4); extra == 'docs'
Requires-Dist: sphinx-rtd-theme; extra == 'docs'
